krutrim_client/__init__.py
krutrim_client/_base_client.py
krutrim_client/_client.py
krutrim_client/_compat.py
krutrim_client/_constants.py
krutrim_client/_exceptions.py
krutrim_client/_files.py
krutrim_client/_models.py
krutrim_client/_qs.py
krutrim_client/_resource.py
krutrim_client/_response.py
krutrim_client/_streaming.py
krutrim_client/_types.py
krutrim_client/_version.py
krutrim_client/py.typed
krutrim_client/_utils/__init__.py
krutrim_client/_utils/_logs.py
krutrim_client/_utils/_proxy.py
krutrim_client/_utils/_reflection.py
krutrim_client/_utils/_resources_proxy.py
krutrim_client/_utils/_streams.py
krutrim_client/_utils/_sync.py
krutrim_client/_utils/_transform.py
krutrim_client/_utils/_typing.py
krutrim_client/_utils/_utils.py
krutrim_client/lib/.keep
krutrim_client/resources/__init__.py
krutrim_client/resources/highlvlvpc.py
krutrim_client/resources/kbs.py
krutrim_client/resources/securityGroup.py
krutrim_client/resources/sshkey.py
krutrim_client/resources/startStopVM.py
krutrim_client/resources/kos/__init__.py
krutrim_client/resources/kos/accessKeys.py
krutrim_client/resources/kos/buckets.py
krutrim_client/resources/kos/kos.py
krutrim_client/resources/kpod/__init__.py
krutrim_client/resources/kpod/kpod.py
krutrim_client/resources/kpod/pod.py
krutrim_client/types/__init__.py
krutrim_client/types/highlvlvpc/__init__.py
krutrim_client/types/highlvlvpc/highlvlvpc_create_image_params.py
krutrim_client/types/highlvlvpc/highlvlvpc_create_image_response.py
krutrim_client/types/highlvlvpc/highlvlvpc_create_instance_params.py
krutrim_client/types/highlvlvpc/highlvlvpc_create_port_params.py
krutrim_client/types/highlvlvpc/highlvlvpc_create_subnet_params.py
krutrim_client/types/highlvlvpc/highlvlvpc_create_vpc_params.py
krutrim_client/types/highlvlvpc/highlvlvpc_delete_image_params.py
krutrim_client/types/highlvlvpc/highlvlvpc_delete_instance_params.py
krutrim_client/types/highlvlvpc/highlvlvpc_delete_machine_image_params.py
krutrim_client-0.4.0.dist-info/METADATA
krutrim_client-0.4.0.dist-info/WHEEL
krutrim_client-0.4.0.dist-info/licenses/LICENSE
krutrim_client-0.4.0.dist-info/RECORD
