Metadata-Version: 2.3
Name: krutrim_client
Version: 0.4.0
Summary: The official Python library for the krutrim_client API
Project-URL: Homepage, https://github.com/ola-krutrim/Krutrim-client-python
Project-URL: Repository, https://github.com/ola-krutrim/Krutrim-client-python
Author-email: Krutrim Client <cloudsupport@olakrutrim.com>
License:                                  Apache License
Classifier: Intended Audience :: Developers
Classifier: License :: OSI Approved :: Apache Software License
Classifier: Operating System :: MacOS
Classifier: Operating System :: Microsoft :: Windows
Classifier: Operating System :: OS Independent
Classifier: Operating System :: POSIX
Classifier: Operating System :: POSIX :: Linux
Classifier: Programming Language :: Python :: 3.8
Classifier: Programming Language :: Python :: 3.9
Classifier: Programming Language :: Python :: 3.10
Classifier: Programming Language :: Python :: 3.11
Classifier: Programming Language :: Python :: 3.12
Classifier: Topic :: Software Development :: Libraries :: Python Modules
Classifier: Typing :: Typed
Requires-Python: >=3.8
Requires-Dist: anyio<5,>=3.5.0
Requires-Dist: distro<2,>=1.7.0
Requires-Dist: httpx<1,>=0.23.0
Requires-Dist: pydantic==2.8.2
Requires-Dist: sniffio
Requires-Dist: typing-extensions<5,>=4.10
